Workbook

Sheet Projections
A1: Three-year financial projections (CAD)
A2: Calculated from editable assumptions; all starting inputs are example placeholders.
A3: Item | B3: Year 1 | C3: Year 2 | D3: Year 3
A4: Revenue | B4: =Assumptions!B4*12 | C4: =B4*(1+Assumptions!C5) | D4: =C4*(1+Assumptions!D5)
A5: Cost of Goods Sold | B5: =B4*Assumptions!B6 | C5: =C4*Assumptions!C6 | D5: =D4*Assumptions!D6
A6: Gross Profit | B6: =B4-B5 | C6: =C4-C5 | D6: =D4-D5
A8: Operating Expenses
A9: Rent | B9: =Assumptions!B8*12 | C9: =Assumptions!C8*12 | D9: =Assumptions!D8*12
A10: Salaries & Wages | B10: =Assumptions!B9*12 | C10: =Assumptions!C9*12 | D10: =Assumptions!D9*12
A11: Marketing | B11: =Assumptions!B10*12 | C11: =Assumptions!C10*12 | D11: =Assumptions!D10*12
A12: Insurance | B12: =Assumptions!B11*12 | C12: =Assumptions!C11*12 | D12: =Assumptions!D11*12
A13: Utilities | B13: =Assumptions!B12*12 | C13: =Assumptions!C12*12 | D13: =Assumptions!D12*12
A14: Other | B14: =Assumptions!B13*12 | C14: =Assumptions!C13*12 | D14: =Assumptions!D13*12
A15: Total Operating Expenses | B15: =SUM(B9:B14) | C15: =SUM(C9:C14) | D15: =SUM(D9:D14)
A17: Net Operating Income | B17: =B6-B15 | C17: =C6-C15 | D17: =D6-D15
A19: Net operating income is before interest, income tax, depreciation and amortisation.
A20: This annual operating forecast is not a cash flow statement or a balance sheet.

Sheet Assumptions
A1: Editable assumptions — CAD, excluding sales taxes
A2: Replace every blue cell before using this template. Zeros are example placeholders, not business data.
A3: Assumption | B3: Year 1 | C3: Year 2 | D3: Year 3 | E3: Basis / evidence (edit)
A4: Average monthly revenue (Year 1 only) | B4: 0 | E4: Enter source, date and rationale
A5: Annual revenue growth rate | C5: 0 | D5: 0 | E5: Enter source, date and rationale
A6: COGS as % of revenue | B6: 0 | C6: 0 | D6: 0 | E6: Enter source, date and rationale
A8: Monthly Rent | B8: 0 | C8: 0 | D8: 0 | E8: Enter source, date and rationale
A9: Monthly Salaries & Wages | B9: 0 | C9: 0 | D9: 0 | E9: Enter source, date and rationale
A10: Monthly Marketing | B10: 0 | C10: 0 | D10: 0 | E10: Enter source, date and rationale
A11: Monthly Insurance | B11: 0 | C11: 0 | D11: 0 | E11: Enter source, date and rationale
A12: Monthly Utilities | B12: 0 | C12: 0 | D12: 0 | E12: Enter source, date and rationale
A13: Monthly Other | B13: 0 | C13: 0 | D13: 0 | E13: Enter source, date and rationale
A16: Business name | B16: Enter here
A17: Forecast start date | B17: Enter here
A18: Prepared by | B18: Enter here
A19: Preparation date | B19: Enter here

Sheet Instructions
A1: Instructions
A2: 1. Identify the business | B2: On Assumptions, record your business name, forecast start date, preparer and preparation date below. Year 1 is the first 12-month forecast period.
A3: 2. Replace example placeholders | B3: Blue cells are editable. Every starting zero is an example placeholder, not actual business data. Enter average monthly Year 1 revenue and annual revenue growth for Years 2 and 3.
A4: 3. Estimate costs | B4: Enter COGS as a percentage for each year (e.g. type 30%). Enter average monthly expenses separately for each year. Salaries & Wages should include employer payroll costs. Do not count costs twice.
A5: 4. Document assumptions | B5: Use the Basis / evidence column for quotes, leases, staffing plans, sales volumes and prices. Use CAD consistently and exclude recoverable GST/HST. Zero growth means revenue stays flat.
A6: 5. Review the projections | B6: Excel recalculates revenue, COGS, gross profit, expense totals and net operating income. Annual amounts use 12 months; monthly averages do not model seasonality. Keep formula cells intact.
A7: 6. Prepare for your lender | B7: Review estimates against historical results and supporting evidence. Include the completed workbook with your business plan; explain growth and downside risks. Ask the bank about required monthly cash flow, balance sheet, capital purchases, financing, debt service and tax schedules.
A8: 7. Save and share | B8: Save a completed copy with the business name and date. Reopen in Excel with automatic calculation enabled and check all three years before submitting. This is a planning template, not a statement of actual results.
